crystallize/__init__.py
crystallize/main.py
crystallize-0.0.10.dist-info/LICENCE
crystallize-0.0.10.dist-info/METADATA
crystallize-0.0.10.dist-info/WHEEL
crystallize-0.0.10.dist-info/top_level.txt
crystallize-0.0.10.dist-info/RECORD
