Metadata-Version: 2.1
Name: crystallize
Version: 0.0.10
Summary: Creating tables and storing them in JSON files
Home-page: https://github.com/duzisnetto/crystallize
Author: Antonio Netto
Author-email: 92.netto@gmail.com
Project-URL: Bug Tracker, https://github.com/duzisnetto/crystallize/issues
Classifier: Programming Language :: Python :: 3
Classifier: License :: OSI Approved :: MIT License
Classifier: Operating System :: OS Independent
Requires-Python: >=3.6
License-File: LICENCE
